{
  "marketing_stripe": {
    "text": "Frete Grátis RS em compras acima de R$120 + brinde exclusivo nas compras acima de R$200 🎁❤️",
    "link": "",
    "color": "#fafafa"
  },
  "contacts_stripe": {
    "pages": [
      {
        "title": "",
        "link": ""
      },
      {
        "title": "",
        "link": ""
      }
    ],
    "phone_wpp": true,
    "socials": true
  },
  "categories_list": {
    "featured": [
      "/capas?Capas",
      "/colecoes?Coleções",
      "/u_10011?Películas",
      "/acessorios?Acessórios",
      "/popsockets?PopSockets"
    ],
    "random": 0,
    "full_width": false
  },
  "search_input": true
}